pyrclone/__init__.py
pyrclone/rclone.py
pyrclone/rclone_config.py
pyrclone-1.0.1.dist-info/LICENSE
pyrclone-1.0.1.dist-info/WHEEL
pyrclone-1.0.1.dist-info/METADATA
pyrclone-1.0.1.dist-info/RECORD
