Metadata-Version: 2.1
Name: pyrclone
Version: 1.0.1
Summary: A typed interface for rclone.
License: GPL-3.0
Author: Ryan C
Author-email: r.cross@lancaster.ac.uk
Requires-Python: >=3.6,<4.0
Classifier: License :: OSI Approved :: GNU General Public License v3 (GPLv3)
Classifier: Programming Language :: Python :: 3
Classifier: Programming Language :: Python :: 3.6
Classifier: Programming Language :: Python :: 3.7
Classifier: Programming Language :: Python :: 3.8
